shplot/__init__.py
shplot/_shplot.py
shplot/_version.py
shplot/profiles/__init__.py
shplot/profiles/_interface.py
shplot/profiles/builtin.py
shplot/py.typed
shplot-1.0.0.dist-info/LICENSE.md
shplot-1.0.0.dist-info/METADATA
shplot-1.0.0.dist-info/WHEEL
shplot-1.0.0.dist-info/RECORD
