Metadata-Version: 2.1
Name: shplot
Version: 1.0.0
Summary: Wrapper for Matplotlib.
Home-page: https://github.com/jayanthkoushik/shplot
License: MIT
Keywords: matplotlib,plotting,dataviz
Author: Jayanth Koushik
Author-email: mail@jkoushik.me
Requires-Python: >=3.9,<4.0
Classifier: Development Status :: 5 - Production/Stable
Classifier: Framework :: Matplotlib
Classifier: Intended Audience :: Developers
Classifier: Intended Audience :: Education
Classifier: Intended Audience :: Science/Research
Classifier: License :: OSI Approved :: MIT License
Classifier: Natural Language :: English
Classifier: Operating System :: OS Independent
Classifier: Programming Language :: Python :: 3
Classifier: Programming Language :: Python :: 3.9
Classifier: Programming Language :: Python :: 3.10
Classifier: Programming Language :: Python :: 3.11
Classifier: Programming Language :: Python :: 3.12
Classifier: Topic :: Utilities
Requires-Dist: corgy (>=9.2,<10.0)
Requires-Dist: matplotlib (>=3.3,<4.0)
Project-URL: Repository, https://github.com/jayanthkoushik/shplot
